LICENSE
MANIFEST.in
README.txt
setup.cfg
setup.py
trelloreporter/__init__.py
trelloreporter/__version__.py
trelloreporter.egg-info/PKG-INFO
trelloreporter.egg-info/SOURCES.txt
trelloreporter.egg-info/dependency_links.txt
trelloreporter.egg-info/entry_points.txt
trelloreporter.egg-info/not-zip-safe
trelloreporter.egg-info/requires.txt
trelloreporter.egg-info/top_level.txt
trelloreporter/cmd/__init__.py
trelloreporter/cmd/trelloreport.py
trelloreporter/cmd/__pycache__/__init__.cpython-35.pyc
trelloreporter/config/__init__.py
trelloreporter/config/trelloreporter.yml
trelloreporter/config/yaml.py
trelloreporter/config/__pycache__/__init__.cpython-35.pyc
trelloreporter/config/__pycache__/yaml.cpython-35.pyc
trelloreporter/data/TrelloReport-2017-12-01.xlsx
trelloreporter/data/TrelloReport-2017-12-07.xlsx
trelloreporter/data/TrelloReport-2017-12-08.xlsx
trelloreporter/data/TrelloReport-2017-12-11.xlsx
trelloreporter/data/TrelloReport-2017-12-12.xlsx
trelloreporter/data/TrelloReport-2017-12-13.xlsx
trelloreporter/data/TrelloReport-2017-12-20.xlsx
trelloreporter/data/trelloreporter.db
trelloreporter/data/log/trelloreporter.log
trelloreporter/rest/__init__.py
trelloreporter/rest/elastic.py
trelloreporter/rest/trello.py
trelloreporter/rest/__pycache__/__init__.cpython-35.pyc
trelloreporter/rest/__pycache__/elastic.cpython-35.pyc
trelloreporter/rest/__pycache__/trello.cpython-35.pyc
trelloreporter/trelloreader/trelloreader.py
trelloreporter/writer/__init__.py
trelloreporter/writer/elastic.py
trelloreporter/writer/excel.py
trelloreporter/writer/trello_data_samples
trelloreporter/writer/__pycache__/__init__.cpython-35.pyc
trelloreporter/writer/__pycache__/excel.cpython-35.pyc